{
  "updatedAt": "2026-06-08T15:03:08.051Z",
  "updatedAtIst": "08/06/2026, 20:33:08",
  "productionDomain": "https://connectintel.net",
  "vercelProject": "connect-intel",
  "currentProductionCommit": "968ad4f",
  "entries": [
    {
      "logId": "20260608-2032-968ad4f",
      "commit": "968ad4f",
      "commitFull": "968ad4f0e24d76e9c11e20d6065870f58d801e53",
      "message": "Improve pipeline bulk email for up to 200 leads with parallel sends and resume.",
      "deployedAt": "2026-06-08T15:02:51.948Z",
      "deployedAtIst": "08/06/2026, 20:32:51",
      "committedAtIst": "08/06/2026, 20:32:26",
      "vercelPreviewUrl": "https://connect-intel-nn2lxuhmn-nee9raj-hues-projects.vercel.app",
      "state": "READY",
      "isCurrentProduction": true,
      "notes": "",
      "rollbackCommand": "npm run prod:rollback -- 968ad4f"
    },
    {
      "logId": "20260608-2025-093bab2",
      "commit": "093bab2",
      "commitFull": "093bab214c1493830155d96552286ee89d501d0f",
      "message": "Update production log for 98298dc timezone and Monday week deploy.",
      "deployedAt": "2026-06-08T14:55:11.624Z",
      "deployedAtIst": "08/06/2026, 20:25:11",
      "committedAtIst": "08/06/2026, 20:24:43",
      "vercelPreviewUrl": "https://connect-intel-1o2gxsbeb-nee9raj-hues-projects.vercel.app",
      "state": "READY",
      "isCurrentProduction": false,
      "notes": "",
      "rollbackCommand": "npm run prod:rollback -- 093bab2"
    },
    {
      "logId": "20260608-2024-98298dc",
      "commit": "98298dc",
      "commitFull": "98298dc52d95e61aa5f2e9e4ff28eb8c31071f36",
      "message": "Use Monday-based calendar weeks and local timezone for periods and dates.",
      "deployedAt": "2026-06-08T14:54:27.670Z",
      "deployedAtIst": "08/06/2026, 20:24:27",
      "committedAtIst": "08/06/2026, 20:23:56",
      "vercelPreviewUrl": "https://connect-intel-mb53ve6j6-nee9raj-hues-projects.vercel.app",
      "state": "READY",
      "isCurrentProduction": false,
      "notes": "",
      "rollbackCommand": "npm run prod:rollback -- 98298dc"
    },
    {
      "logId": "20260608-2016-d810ae7",
      "commit": "d810ae7",
      "commitFull": "d810ae7946b57ffe67ee78d1fda97a7f3b0ee2ac",
      "message": "Update production log for 455806b activity pagination deploy.",
      "deployedAt": "2026-06-08T14:46:09.635Z",
      "deployedAtIst": "08/06/2026, 20:16:09",
      "committedAtIst": "08/06/2026, 20:15:41",
      "vercelPreviewUrl": "https://connect-intel-3nxlepyay-nee9raj-hues-projects.vercel.app",
      "state": "READY",
      "isCurrentProduction": false,
      "notes": "",
      "rollbackCommand": "npm run prod:rollback -- d810ae7"
    },
    {
      "logId": "20260608-2015-455806b",
      "commit": "455806b",
      "commitFull": "455806ba62829af0358028f69912c0878396ab30",
      "message": "Paginate Team Intelligence detailed activity to five rows with load more.",
      "deployedAt": "2026-06-08T14:45:21.776Z",
      "deployedAtIst": "08/06/2026, 20:15:21",
      "committedAtIst": "08/06/2026, 20:14:54",
      "vercelPreviewUrl": "https://connect-intel-kwinca27d-nee9raj-hues-projects.vercel.app",
      "state": "READY",
      "isCurrentProduction": false,
      "notes": "",
      "rollbackCommand": "npm run prod:rollback -- 455806b"
    },
    {
      "logId": "20260608-2005-925bced",
      "commit": "925bced",
      "commitFull": "925bced36b3f8cf38ba7db704d843eb87de55541",
      "message": "Update production log for b3a9f3b Team Intelligence upgrade deploy.",
      "deployedAt": "2026-06-08T14:35:56.885Z",
      "deployedAtIst": "08/06/2026, 20:05:56",
      "committedAtIst": "08/06/2026, 20:05:27",
      "vercelPreviewUrl": "https://connect-intel-mwbftfxs4-nee9raj-hues-projects.vercel.app",
      "state": "READY",
      "isCurrentProduction": false,
      "notes": "",
      "rollbackCommand": "npm run prod:rollback -- 925bced"
    },
    {
      "logId": "20260608-2005-b3a9f3b",
      "commit": "b3a9f3b",
      "commitFull": "b3a9f3b6f6d79e8d6e3548cbb10cede10f8e5d5e",
      "message": "Upgrade Team Intelligence with filter counts, roster selection, and activity detail modals.",
      "deployedAt": "2026-06-08T14:35:03.829Z",
      "deployedAtIst": "08/06/2026, 20:05:03",
      "committedAtIst": "08/06/2026, 20:04:26",
      "vercelPreviewUrl": "https://connect-intel-3jifbmn2c-nee9raj-hues-projects.vercel.app",
      "state": "READY",
      "isCurrentProduction": false,
      "notes": "",
      "rollbackCommand": "npm run prod:rollback -- b3a9f3b"
    },
    {
      "logId": "20260608-1948-3a03a29",
      "commit": "3a03a29",
      "commitFull": "3a03a29ca89166efe866713113fbaa24db38245f",
      "message": "Add full Team Intelligence page for manager rep reviews.",
      "deployedAt": "2026-06-08T14:18:42.461Z",
      "deployedAtIst": "08/06/2026, 19:48:42",
      "committedAtIst": "08/06/2026, 19:48:14",
      "vercelPreviewUrl": "https://connect-intel-6wqix7pis-nee9raj-hues-projects.vercel.app",
      "state": "READY",
      "isCurrentProduction": false,
      "notes": "",
      "rollbackCommand": "npm run prod:rollback -- 3a03a29"
    },
    {
      "logId": "20260608-1934-fb040ab",
      "commit": "fb040ab",
      "commitFull": "fb040aba58cb8b78c9104e2058a7317e33b119fa",
      "message": "Speed up CRM load with precomputed pipeline index and bootstrap API.",
      "deployedAt": "2026-06-08T14:04:52.211Z",
      "deployedAtIst": "08/06/2026, 19:34:52",
      "committedAtIst": "08/06/2026, 19:34:23",
      "vercelPreviewUrl": "https://connect-intel-hshadiqob-nee9raj-hues-projects.vercel.app",
      "state": "READY",
      "isCurrentProduction": false,
      "notes": "",
      "rollbackCommand": "npm run prod:rollback -- fb040ab"
    },
    {
      "logId": "20260608-1918-8d39bf2",
      "commit": "8d39bf2",
      "commitFull": "8d39bf21eaad2ec46b4974aa8bfafb78f1756d30",
      "message": "Fix Ludhiana textile search: ignore india keyword, restore live AI fallback.",
      "deployedAt": "2026-06-08T13:48:31.763Z",
      "deployedAtIst": "08/06/2026, 19:18:31",
      "committedAtIst": "08/06/2026, 19:18:03",
      "vercelPreviewUrl": "https://connect-intel-38gtiwjs3-nee9raj-hues-projects.vercel.app",
      "state": "READY",
      "isCurrentProduction": false,
      "notes": "",
      "rollbackCommand": "npm run prod:rollback -- 8d39bf2"
    },
    {
      "logId": "20260608-1911-251c96d",
      "commit": "251c96d",
      "commitFull": "251c96dc887cf738a092e1a0c6512535767f593c",
      "message": "Fix search timeout by avoiding full-store quota reads/writes.",
      "deployedAt": "2026-06-08T13:41:19.387Z",
      "deployedAtIst": "08/06/2026, 19:11:19",
      "committedAtIst": "08/06/2026, 19:10:51",
      "vercelPreviewUrl": "https://connect-intel-7vl9u70bk-nee9raj-hues-projects.vercel.app",
      "state": "READY",
      "isCurrentProduction": false,
      "notes": "",
      "rollbackCommand": "npm run prod:rollback -- 251c96d"
    },
    {
      "logId": "20260608-1710-7584d6b",
      "commit": "7584d6b",
      "commitFull": "7584d6b10ef65eb99f5d5590df458a67579ec07d",
      "message": "Log production deploy 328295d (AI search database-first).",
      "deployedAt": "2026-06-08T11:40:29.876Z",
      "deployedAtIst": "08/06/2026, 17:10:29",
      "committedAtIst": "08/06/2026, 17:10:01",
      "vercelPreviewUrl": "https://connect-intel-kamnnmsfn-nee9raj-hues-projects.vercel.app",
      "state": "READY",
      "isCurrentProduction": false,
      "notes": "",
      "rollbackCommand": "npm run prod:rollback -- 7584d6b"
    },
    {
      "logId": "20260608-1709-328295d",
      "commit": "328295d",
      "commitFull": "328295d665d25f03237cb4736d5e2a159345ac61",
      "message": "Fix AI search timeouts by querying the database before live AI.",
      "deployedAt": "2026-06-08T11:39:30.505Z",
      "deployedAtIst": "08/06/2026, 17:09:30",
      "committedAtIst": "08/06/2026, 17:09:03",
      "vercelPreviewUrl": "https://connect-intel-fo1odk44n-nee9raj-hues-projects.vercel.app",
      "state": "READY",
      "isCurrentProduction": false,
      "notes": "",
      "rollbackCommand": "npm run prod:rollback -- 328295d"
    },
    {
      "logId": "20260608-1703-b91ead0",
      "commit": "b91ead0",
      "commitFull": "b91ead0d47e4195430a7f419e22b80945fb059bf",
      "message": "Log production deploy c87e73e (AI search dedupe and real DB results).",
      "deployedAt": "2026-06-08T11:33:38.812Z",
      "deployedAtIst": "08/06/2026, 17:03:38",
      "committedAtIst": "08/06/2026, 17:03:11",
      "vercelPreviewUrl": "https://connect-intel-e562ipxpz-nee9raj-hues-projects.vercel.app",
      "state": "READY",
      "isCurrentProduction": false,
      "notes": "",
      "rollbackCommand": "npm run prod:rollback -- b91ead0"
    },
    {
      "logId": "20260608-1702-c87e73e",
      "commit": "c87e73e",
      "commitFull": "c87e73e7960b0d30c54165e9005fb9fde847ac2e",
      "message": "Fix AI search showing one repeated mock lead instead of real database results.",
      "deployedAt": "2026-06-08T11:32:40.348Z",
      "deployedAtIst": "08/06/2026, 17:02:40",
      "committedAtIst": "08/06/2026, 17:02:13",
      "vercelPreviewUrl": "https://connect-intel-9y3kadio0-nee9raj-hues-projects.vercel.app",
      "state": "READY",
      "isCurrentProduction": false,
      "notes": "",
      "rollbackCommand": "npm run prod:rollback -- c87e73e"
    },
    {
      "logId": "20260608-1656-e2be456",
      "commit": "e2be456",
      "commitFull": "e2be456a5135710dc81f78ca471510a33284eb00",
      "message": "Log production deploy 4899d0d (import timeout and dedupe fixes).",
      "deployedAt": "2026-06-08T11:26:08.621Z",
      "deployedAtIst": "08/06/2026, 16:56:08",
      "committedAtIst": "08/06/2026, 16:55:40",
      "vercelPreviewUrl": "https://connect-intel-agi8927p6-nee9raj-hues-projects.vercel.app",
      "state": "READY",
      "isCurrentProduction": false,
      "notes": "",
      "rollbackCommand": "npm run prod:rollback -- e2be456"
    },
    {
      "logId": "20260608-1655-4899d0d",
      "commit": "4899d0d",
      "commitFull": "4899d0d6ab388c00cd6d77d9bcd800be7aacb702",
      "message": "Fix master DB import timeouts and add duplicate cleanup.",
      "deployedAt": "2026-06-08T11:25:06.932Z",
      "deployedAtIst": "08/06/2026, 16:55:06",
      "committedAtIst": "08/06/2026, 16:54:38",
      "vercelPreviewUrl": "https://connect-intel-8btknavc4-nee9raj-hues-projects.vercel.app",
      "state": "READY",
      "isCurrentProduction": false,
      "notes": "",
      "rollbackCommand": "npm run prod:rollback -- 4899d0d"
    },
    {
      "logId": "20260608-1649-4b4d3d7",
      "commit": "4b4d3d7",
      "commitFull": "4b4d3d7ec32faf9febe89ac833fff0ea15f52152",
      "message": "Log production deploy daa6f20 (chunked imports and operator console).",
      "deployedAt": "2026-06-08T11:19:58.590Z",
      "deployedAtIst": "08/06/2026, 16:49:58",
      "committedAtIst": "08/06/2026, 16:49:28",
      "vercelPreviewUrl": "https://connect-intel-5ywngeyt9-nee9raj-hues-projects.vercel.app",
      "state": "READY",
      "isCurrentProduction": false,
      "notes": "",
      "rollbackCommand": "npm run prod:rollback -- 4b4d3d7"
    },
    {
      "logId": "20260608-1648-daa6f20",
      "commit": "daa6f20",
      "commitFull": "daa6f204cca35808f0435704d8f4263736392b01",
      "message": "Fix large platform imports and expand operator admin console.",
      "deployedAt": "2026-06-08T11:18:54.558Z",
      "deployedAtIst": "08/06/2026, 16:48:54",
      "committedAtIst": "08/06/2026, 16:48:25",
      "vercelPreviewUrl": "https://connect-intel-g49ihyidj-nee9raj-hues-projects.vercel.app",
      "state": "READY",
      "isCurrentProduction": false,
      "notes": "",
      "rollbackCommand": "npm run prod:rollback -- daa6f20"
    },
    {
      "logId": "20260608-1442-c61fe98",
      "commit": "c61fe98",
      "commitFull": "c61fe98d368fa3fa921296abd1188945caa4999c",
      "message": "Log production deploy 8d704f3 (navigation and reporting drill-downs).",
      "deployedAt": "2026-06-08T09:12:00.672Z",
      "deployedAtIst": "08/06/2026, 14:42:00",
      "committedAtIst": "08/06/2026, 14:41:33",
      "vercelPreviewUrl": "https://connect-intel-ipgy2qk9f-nee9raj-hues-projects.vercel.app",
      "state": "READY",
      "isCurrentProduction": false,
      "notes": "",
      "rollbackCommand": "npm run prod:rollback -- c61fe98"
    }
  ]
}
